dash_id_manager/__init__.py
dash_id_manager/base_ids.py
dash_id_manager-1.0.6.dist-info/LICENSE.md
dash_id_manager-1.0.6.dist-info/METADATA
dash_id_manager-1.0.6.dist-info/WHEEL
dash_id_manager-1.0.6.dist-info/top_level.txt
dash_id_manager-1.0.6.dist-info/RECORD
