Metadata-Version: 2.1
Name: dash-id-manager
Version: 1.0.6
Summary: Efficient id manager for Plotly Dash.
Home-page: https://github.com/Dencyuman/dash-id-manager
Download-URL: https://github.com/Dencyuman/dash-id-manager
Author: Dencyuman
Author-email: Dencyuman <takotakocyuman@gmail.com>
Maintainer: Dencyuman
Maintainer-email: takotakocyuman@gmail.com
Requires-Python: >=3.7
License-File: LICENSE.md
